setup.py
src/automium.py
src/atm/__init__.py
src/atm/base.py
src/atm/build.py
src/atm/environ.py
src/atm/exceptions.py
src/atm/hash.py
src/atm/load.py
src/atm/pack.py
src/atm/repo.py
src/atm/static.py
src/atm/test.py
src/automium.egg-info/PKG-INFO
src/automium.egg-info/SOURCES.txt
src/automium.egg-info/dependency_links.txt
src/automium.egg-info/entry_points.txt
src/automium.egg-info/requires.txt
src/automium.egg-info/top_level.txt
src/automium.egg-info/zip-safe