Metadata-Version: 1.1
Name: automium
Version: 0.2.4
Summary: Automium System
Home-page: http://automium.hive.pt
Author: Hive Solutions Lda.
Author-email: development@hive.pt
License: Apache License, Version 2.0
Keywords: automium build automation console
Platform: UNKNOWN
Classifier: Development Status :: 5 - Production/Stable
Classifier: Topic :: Utilities
Classifier: License :: OSI Approved :: Apache Software License
Classifier: Operating System :: OS Independent
Classifier: Programming Language :: Python
Classifier: Programming Language :: Python :: 2.6
Classifier: Programming Language :: Python :: 2.7
Classifier: Programming Language :: Python :: 3.0
Classifier: Programming Language :: Python :: 3.1
Classifier: Programming Language :: Python :: 3.2
Classifier: Programming Language :: Python :: 3.3
Classifier: Programming Language :: Python :: 3.4
